Metadata-Version: 2.1
Name: thirtysevena
Version: 1.0
Summary: 37AUSTEN's Proprietary Algorithms Library.
Home-page: https://github.com/37austen/37austen-python
Author: 37AUSTEN
Author-email: hello@37austen.com
License: MIT
Keywords: data analytics,finance,risk,market volatility
Platform: UNKNOWN
Classifier: Development Status :: 5 - Production/Stable
Classifier: Intended Audience :: Developers
Classifier: Intended Audience :: Financial and Insurance Industry
Classifier: Intended Audience :: Science/Research
Classifier: Natural Language :: English
Classifier: License :: OSI Approved :: MIT License
Classifier: Operating System :: Microsoft :: Windows
Classifier: Operating System :: MacOS
Classifier: Programming Language :: Python :: 3.6
Classifier: Programming Language :: Python :: 3.7
Classifier: Programming Language :: Python :: 3.8
Classifier: Programming Language :: Python :: 3.9
